{"0":{"Campbells":8,"Cup":0,"Progresso":47},"1":{"Campbells":49,"Cup":3,"Progresso":21},"10":{"Campbells":151,"Cup":12,"Progresso":33},"11":{"Campbells":45,"Cup":0,"Progresso":28},"12":{"Campbells":62,"Cup":1,"Progresso":26},"13":{"Campbells":16,"Cup":0,"Progresso":38},"14":{"Campbells":47,"Cup":0,"Progresso":17},"15":{"Campbells":0,"Cup":0,"Progresso":22},"16":{"Campbells":0,"Cup":0,"Progresso":25},"17":{"Campbells":108,"Cup":1,"Progresso":22},"18":{"Campbells":24,"Cup":0,"Progresso":1},"19":{"Campbells":26,"Cup":0,"Progresso":59},"2":{"Campbells":42,"Cup":0,"Progresso":45},"3":{"Campbells":63,"Cup":4,"Progresso":2},"4":{"Campbells":44,"Cup":0,"Progresso":2},"5":{"Campbells":58,"Cup":0,"Progresso":33},"6":{"Campbells":75,"Cup":0,"Progresso":15},"7":{"Campbells":14,"Cup":0,"Progresso":43},"8":{"Campbells":87,"Cup":0,"Progresso":28},"9":{"Campbells":89,"Cup":2,"Progresso":3}}